<Ui xmlns="http://www.blizzard.com/wow/ui/" 
	xmlns:xsi="http://www.w3.org/2001/XMLSchema-instance" 
	xsi:schemaLocation="http://www.blizzard.com/wow/ui/">
	
<!--
	Total RP 3
	Copyright 2014-2016 Sylvain Cossement (telkostrasz@totalrp3.info)

	Licensed under the Apache License, Version 2.0 (the "License");
	you may not use this file except in compliance with the License.
	You may obtain a copy of the License at

		http://www.apache.org/licenses/LICENSE-2.0

	Unless required by applicable law or agreed to in writing, software
	distributed under the License is distributed on an "AS IS" BASIS,
	WITHOUT WARRANTIES OR CONDITIONS OF ANY KIND, either express or implied.
	See the License for the specific language governing permissions and
	limitations under the License.
-->

	<Frame name="TRP3_OperandEditorUnitType" hidden="true">
		<Frames>
			<Frame parentKey="type" inherits="TRP3_DropDownMenuTemplate" enableMouse="true" name="$parentType">
				<Anchors>
					<Anchor point="LEFT" x="0" y="0"/>
				</Anchors>
			</Frame>
		</Frames>
	</Frame>

	<Frame name="TRP3_OperandEditorString" hidden="true">
		<Frames>
			<EditBox parentKey="input" inherits="TRP3_TitledHelpEditBox">
				<Anchors>
					<Anchor point="LEFT" x="15" y="0"/>
					<Anchor point="RIGHT" x="-15" y="0"/>
				</Anchors>
			</EditBox>
		</Frames>
	</Frame>

	<Frame name="TRP3_OperandEditorNumeric" hidden="true">
		<Frames>
			<EditBox parentKey="input" inherits="TRP3_TitledHelpEditBox">
				<Anchors>
					<Anchor point="LEFT" x="15" y="0"/>
					<Anchor point="RIGHT" x="-15" y="0"/>
				</Anchors>
			</EditBox>
		</Frames>
	</Frame>

	<Frame name="TRP3_OperandEditorCheckVar" hidden="true">
		<Frames>
			<Frame parentKey="source" inherits="TRP3_DropDownMenuTemplate" enableMouse="true" name="$parentType">
				<Anchors>
					<Anchor point="TOP" x="0" y="-45"/>
				</Anchors>
			</Frame>
			<EditBox parentKey="var" inherits="TRP3_TitledHelpEditBox">
				<Anchors>
					<Anchor point="TOP" relativePoint="BOTTOM" relativeKey="$parent.source" x="0" y="-10"/>
					<Anchor point="LEFT" x="15" y="0"/>
					<Anchor point="RIGHT" x="-15" y="0"/>
				</Anchors>
			</EditBox>
		</Frames>
	</Frame>

	<Frame name="TRP3_OperandEditorCheckEventArg" hidden="true">
		<Frames>
			<EditBox parentKey="index" inherits="TRP3_TitledHelpEditBox">
				<Anchors>
					<Anchor point="TOP" x="0" y="-45"/>
					<Anchor point="LEFT" x="15" y="0"/>
					<Anchor point="RIGHT" x="-15" y="0"/>
				</Anchors>
			</EditBox>
		</Frames>
	</Frame>

	<Frame name="TRP3_OperandEditorDistancePoint" hidden="true">
		<Frames>
			<Frame parentKey="type" inherits="TRP3_DropDownMenuTemplate" enableMouse="true" name="$parentType">
				<Anchors>
					<Anchor point="TOP" x="0" y="-25"/>
				</Anchors>
			</Frame>
			<EditBox parentKey="x" inherits="TRP3_TitledHelpEditBox">
				<Anchors>
					<Anchor point="TOP" relativePoint="BOTTOM" relativeKey="$parent.type" x="0" y="-10"/>
					<Anchor point="LEFT" x="15" y="0"/>
					<Anchor point="RIGHT" relativePoint="CENTER" x="-10" y="0"/>
				</Anchors>
			</EditBox>
			<EditBox parentKey="y" inherits="TRP3_TitledHelpEditBox">
				<Anchors>
					<Anchor point="TOP" relativePoint="BOTTOM" relativeKey="$parent.type" x="0" y="-10"/>
					<Anchor point="LEFT" relativePoint="CENTER" x="10" y="0"/>
					<Anchor point="RIGHT" x="-15" y="0"/>
				</Anchors>
			</EditBox>
			<Button parentKey="current" inherits="TRP3_CommonButton">
				<Anchors>
					<Anchor point="TOPLEFT" relativePoint="BOTTOMLEFT" relativeKey="$parent.x" x="0" y="-5"/>
					<Anchor point="TOPRIGHT" relativePoint="BOTTOMRIGHT" relativeKey="$parent.y" x="0" y="-5"/>
				</Anchors>
			</Button>
		</Frames>
	</Frame>

	<Frame name="TRP3_OperandEditorRandom" hidden="true">
		<Frames>
			<EditBox parentKey="from" inherits="TRP3_TitledHelpEditBox">
				<Anchors>
					<Anchor point="TOP" x="0" y="-45"/>
					<Anchor point="LEFT" x="15" y="0"/>
					<Anchor point="RIGHT" x="-15" y="0"/>
				</Anchors>
			</EditBox>

			<EditBox parentKey="to" inherits="TRP3_TitledHelpEditBox">
				<Anchors>
					<Anchor point="TOP" relativePoint="BOTTOM" relativeKey="$parent.from" x="0" y="-10"/>
					<Anchor point="LEFT" x="15" y="0"/>
					<Anchor point="RIGHT" x="-15" y="0"/>
				</Anchors>
			</EditBox>
		</Frames>
	</Frame>

	<Frame name="TRP3_OperandEditorAchievementSelection" hidden="true">
		<Frames>
			<Frame parentKey="type" inherits="TRP3_DropDownMenuTemplate" enableMouse="true" name="$parentType">
				<Anchors>
					<Anchor point="TOP" x="0" y="-25"/>
				</Anchors>
			</Frame>
			<EditBox parentKey="id" inherits="TRP3_TitledHelpEditBox">
				<Anchors>
					<Anchor point="TOP" relativePoint="BOTTOM" relativeKey="$parent.type" x="0" y="-10"/>
					<Anchor point="LEFT" x="15" y="0"/>
					<Anchor point="RIGHT" x="-15" y="0"/>
				</Anchors>
			</EditBox>
		</Frames>
	</Frame>
	
</Ui>